odoo8_addon_l10n_es_aeat_sii_oss-8.0.1.0.0.99.dev2-py3.8-nspkg.pth
odoo_addons/l10n_es_aeat_sii_oss/README.rst
odoo_addons/l10n_es_aeat_sii_oss/__init__.py
odoo_addons/l10n_es_aeat_sii_oss/__openerp__.py
odoo_addons/l10n_es_aeat_sii_oss/data/aeat_sii_mapping_registration_keys_data.xml
odoo_addons/l10n_es_aeat_sii_oss/i18n/l10n_es_aeat_sii_oss.pot
odoo_addons/l10n_es_aeat_sii_oss/models/__init__.py
odoo_addons/l10n_es_aeat_sii_oss/models/account_invoice.py
odoo_addons/l10n_es_aeat_sii_oss/readme/CONFIGURE.rst
odoo_addons/l10n_es_aeat_sii_oss/readme/CONTRIBUTORS.rst
odoo_addons/l10n_es_aeat_sii_oss/readme/DESCRIPTION.rst
odoo_addons/l10n_es_aeat_sii_oss/readme/INSTALL.rst
odoo_addons/l10n_es_aeat_sii_oss/static/description/icon.png
odoo_addons/l10n_es_aeat_sii_oss/static/description/icon_source.svg
odoo_addons/l10n_es_aeat_sii_oss/static/description/index.html
odoo_addons/l10n_es_aeat_sii_oss/tests/__init__.py
odoo_addons/l10n_es_aeat_sii_oss/tests/test_l10n_es_aeat_sii.py
odoo8_addon_l10n_es_aeat_sii_oss-8.0.1.0.0.99.dev2.dist-info/METADATA
odoo8_addon_l10n_es_aeat_sii_oss-8.0.1.0.0.99.dev2.dist-info/WHEEL
odoo8_addon_l10n_es_aeat_sii_oss-8.0.1.0.0.99.dev2.dist-info/namespace_packages.txt
odoo8_addon_l10n_es_aeat_sii_oss-8.0.1.0.0.99.dev2.dist-info/top_level.txt
odoo8_addon_l10n_es_aeat_sii_oss-8.0.1.0.0.99.dev2.dist-info/RECORD
